[
    {
        "csn": "1078363700",
        "mrn": "46013386",
        "name": "Lisa Aguirre",
        "dob": "1929-10-28",
        "sex": "F",
        "ethnicity": [
            "Not Stated / Unknown"
        ],
        "postcode": "46411",
        "admission_dt": "2021-12-20T17:16:00+00:00",
        "discharge_dt": null,
        "bed_code": "BY02-17",
        "bay_code": "BY02",
        "bay_type": "Regular",
        "ward_code": "T03"
    },
    {
        "csn": "1041677024",
        "mrn": "45570713",
        "name": "Kenneth Lewis",
        "dob": "1998-08-19",
        "sex": "M",
        "ethnicity": [
            null
        ],
        "postcode": "16644",
        "admission_dt": "2021-12-21T21:37:00+00:00",
        "discharge_dt": null,
        "bed_code": "BY02-18",
        "bay_code": "BY02",
        "bay_type": "Regular",
        "ward_code": "T03"
    },
    {
        "csn": "1073549104",
        "mrn": "47981456",
        "name": "Sean Thomas",
        "dob": "1995-06-05",
        "sex": "M",
        "ethnicity": [
            "Other Ethnic Group"
        ],
        "postcode": "74041",
        "admission_dt": "2021-12-05T21:05:00+00:00",
        "discharge_dt": null,
        "bed_code": "BY02-19",
        "bay_code": "BY02",
        "bay_type": "Regular",
        "ward_code": "T03"
    },
    {
        "csn": "1094753147",
        "mrn": "48166587",
        "name": "Sean Hanson",
        "dob": "1954-04-30",
        "sex": "M",
        "ethnicity": [
            "White British"
        ],
        "postcode": "07459",
        "admission_dt": "2021-12-21T22:51:00+00:00",
        "discharge_dt": null,
        "bed_code": "BY02-20",
        "bay_code": "BY02",
        "bay_type": "Regular",
        "ward_code": "T03"
    },
    {
        "csn": "1087442835",
        "mrn": "41900570",
        "name": "Cynthia Lloyd",
        "dob": "1973-03-18",
        "sex": "F",
        "ethnicity": [
            null
        ],
        "postcode": "02381",
        "admission_dt": "2021-12-13T23:42:00+00:00",
        "discharge_dt": null,
        "bed_code": "BY02-21",
        "bay_code": "BY02",
        "bay_type": "Regular",
        "ward_code": "T03"
    },
    {
        "csn": "1040826469",
        "mrn": "40962056",
        "name": "Brian Romero",
        "dob": "1970-10-23",
        "sex": "M",
        "ethnicity": [
            "White British"
        ],
        "postcode": "21027",
        "admission_dt": "2021-12-21T11:18:00+00:00",
        "discharge_dt": null,
        "bed_code": "BY03-22",
        "bay_code": "BY03",
        "bay_type": "Regular",
        "ward_code": "T03"
    },
    {
        "csn": "1057753240",
        "mrn": "43208066",
        "name": "Sara Watson",
        "dob": "1919-01-01",
        "sex": "F",
        "ethnicity": [
            "Other Ethnic Group"
        ],
        "postcode": "18873",
        "admission_dt": "2021-12-22T18:16:00+00:00",
        "discharge_dt": null,
        "bed_code": "BY03-23",
        "bay_code": "BY03",
        "bay_type": "Regular",
        "ward_code": "T03"
    },
    {
        "csn": "1033167639",
        "mrn": "47118100",
        "name": "Aaron Key",
        "dob": "1927-06-11",
        "sex": "M",
        "ethnicity": [
            "White Irish"
        ],
        "postcode": "02152",
        "admission_dt": "2021-12-20T19:57:00+00:00",
        "discharge_dt": null,
        "bed_code": "BY03-24",
        "bay_code": "BY03",
        "bay_type": "Regular",
        "ward_code": "T03"
    },
    {
        "csn": "1031609494",
        "mrn": "47353042",
        "name": "Justin Collier",
        "dob": "1984-06-24",
        "sex": "M",
        "ethnicity": [
            "Not Yet Asked"
        ],
        "postcode": "84492",
        "admission_dt": "2021-12-21T17:17:00+00:00",
        "discharge_dt": null,
        "bed_code": "BY03-25",
        "bay_code": "BY03",
        "bay_type": "Regular",
        "ward_code": "T03"
    },
    {
        "csn": "1097196341",
        "mrn": "40523642",
        "name": "Charles Foster",
        "dob": "1966-10-15",
        "sex": "M",
        "ethnicity": [
            "Other Ethnic Group"
        ],
        "postcode": "78902",
        "admission_dt": "2021-12-20T14:50:00+00:00",
        "discharge_dt": null,
        "bed_code": "BY03-26",
        "bay_code": "BY03",
        "bay_type": "Regular",
        "ward_code": "T03"
    },
    {
        "csn": "1010868185",
        "mrn": "47635246",
        "name": "William Martin",
        "dob": "1931-02-08",
        "sex": "M",
        "ethnicity": [
            "White British"
        ],
        "postcode": "82070",
        "admission_dt": "2021-12-08T22:42:00+00:00",
        "discharge_dt": null,
        "bed_code": "BY04-28",
        "bay_code": "BY04",
        "bay_type": "Regular",
        "ward_code": "T03"
    },
    {
        "csn": "1044100844",
        "mrn": "44883631",
        "name": "Briana Lynn",
        "dob": "2013-04-22",
        "sex": "F",
        "ethnicity": [
            "White British"
        ],
        "postcode": "01128",
        "admission_dt": "2021-12-22T16:18:00+00:00",
        "discharge_dt": null,
        "bed_code": "BY04-29",
        "bay_code": "BY04",
        "bay_type": "Regular",
        "ward_code": "T03"
    },
    {
        "csn": "1080384753",
        "mrn": "42830415",
        "name": "Leslie Leach",
        "dob": "1932-06-05",
        "sex": "F",
        "ethnicity": [
            "White British"
        ],
        "postcode": "49546",
        "admission_dt": "2021-12-15T03:46:00+00:00",
        "discharge_dt": null,
        "bed_code": "BY04-30",
        "bay_code": "BY04",
        "bay_type": "Regular",
        "ward_code": "T03"
    },
    {
        "csn": "1088690757",
        "mrn": "47572614",
        "name": "Amanda Green",
        "dob": "1993-10-19",
        "sex": "F",
        "ethnicity": [
            "Not Yet Asked"
        ],
        "postcode": "20712",
        "admission_dt": "2021-12-22T17:15:00+00:00",
        "discharge_dt": null,
        "bed_code": "BY04-31",
        "bay_code": "BY04",
        "bay_type": "Regular",
        "ward_code": "T03"
    },
    {
        "csn": "1042005241",
        "mrn": "45500614",
        "name": "Kevin Wilkinson",
        "dob": "1934-03-02",
        "sex": "M",
        "ethnicity": [
            "Not Yet Asked"
        ],
        "postcode": "12922",
        "admission_dt": "2021-12-18T20:02:00+00:00",
        "discharge_dt": null,
        "bed_code": "BY05-34",
        "bay_code": "BY05",
        "bay_type": "Regular",
        "ward_code": "T03"
    },
    {
        "csn": "1053426405",
        "mrn": "45329552",
        "name": "Kristi Wilson",
        "dob": "1918-02-13",
        "sex": "F",
        "ethnicity": [
            "White British"
        ],
        "postcode": "36147",
        "admission_dt": "2021-12-21T21:04:00+00:00",
        "discharge_dt": null,
        "bed_code": "SR02-02",
        "bay_code": "SR02",
        "bay_type": "SideRoom",
        "ward_code": "T03"
    },
    {
        "csn": "1076553240",
        "mrn": "42121701",
        "name": "Kimberly Young",
        "dob": "1958-06-03",
        "sex": "F",
        "ethnicity": [
            "White Irish"
        ],
        "postcode": "40883",
        "admission_dt": "2021-12-10T21:44:00+00:00",
        "discharge_dt": null,
        "bed_code": "SR03-03",
        "bay_code": "SR03",
        "bay_type": "SideRoom",
        "ward_code": "T03"
    },
    {
        "csn": "1073869638",
        "mrn": "43872601",
        "name": "Jason Brooks",
        "dob": "1988-12-23",
        "sex": "M",
        "ethnicity": [
            "White British"
        ],
        "postcode": "39734",
        "admission_dt": "2021-12-16T23:11:00+00:00",
        "discharge_dt": null,
        "bed_code": "SR05-05",
        "bay_code": "SR05",
        "bay_type": "SideRoom",
        "ward_code": "T03"
    },
    {
        "csn": "1009045834",
        "mrn": "48154635",
        "name": "Jeremy Lane",
        "dob": "1920-09-14",
        "sex": "M",
        "ethnicity": [
            "Other Ethnic Group"
        ],
        "postcode": "60961",
        "admission_dt": "2021-12-07T11:32:00+00:00",
        "discharge_dt": null,
        "bed_code": "SR06-06",
        "bay_code": "SR06",
        "bay_type": "SideRoom",
        "ward_code": "T03"
    },
    {
        "csn": "1053399542",
        "mrn": "47743186",
        "name": "Gregory Vance",
        "dob": "2007-08-25",
        "sex": "M",
        "ethnicity": [
            "White British"
        ],
        "postcode": "20288",
        "admission_dt": "2021-12-11T13:39:00+00:00",
        "discharge_dt": null,
        "bed_code": "SR07-07",
        "bay_code": "SR07",
        "bay_type": "SideRoom",
        "ward_code": "T03"
    },
    {
        "csn": "1087007685",
        "mrn": "44576703",
        "name": "Pamela French",
        "dob": "1945-11-21",
        "sex": "F",
        "ethnicity": [
            "Not Stated / Unknown"
        ],
        "postcode": "72614",
        "admission_dt": "2021-12-19T00:54:00+00:00",
        "discharge_dt": null,
        "bed_code": "SR08-08",
        "bay_code": "SR08",
        "bay_type": "SideRoom",
        "ward_code": "T03"
    },
    {
        "csn": "1090945271",
        "mrn": "44703184",
        "name": "Richard Davis",
        "dob": "1935-07-29",
        "sex": "M",
        "ethnicity": [
            "Other Ethnic Group"
        ],
        "postcode": "45883",
        "admission_dt": "2021-12-19T16:44:00+00:00",
        "discharge_dt": null,
        "bed_code": "SR10-10",
        "bay_code": "SR10",
        "bay_type": "SideRoom",
        "ward_code": "T03"
    },
    {
        "csn": "1080364189",
        "mrn": "47768504",
        "name": "Daniel Palmer",
        "dob": "2004-09-01",
        "sex": "M",
        "ethnicity": [
            "Other Ethnic Group"
        ],
        "postcode": "79149",
        "admission_dt": "2021-12-14T08:26:00+00:00",
        "discharge_dt": null,
        "bed_code": "SR32-32",
        "bay_code": "SR32",
        "bay_type": "SideRoom",
        "ward_code": "T03"
    }
]